rtpTTML/__init__.py
rtpTTML/py.typed
rtpTTML/ttmlReceiver.py
rtpTTML/ttmlTransmitter.py
rtpTTML-0.0.2.dist-info/METADATA
rtpTTML-0.0.2.dist-info/WHEEL
rtpTTML-0.0.2.dist-info/top_level.txt
rtpTTML-0.0.2.dist-info/RECORD
