Metadata-Version: 2.1
Name: rtpTTML
Version: 0.0.2
Summary: A library for transmitting/receiving TTML over RTP
Home-page: https://github.com/bbc/rd-apmm-python-lib-rtpTTML
Author: BBC R&D
Author-email: cloudfit-opensource@rd.bbc.co.uk
License: apache-2.0
Requires-Dist: mypy
Requires-Dist: lxml
Requires-Dist: rtp
Requires-Dist: rtpPayload-ttml
